flask_starterkit-0.2.0.dist-info/DESCRIPTION.rst
flask_starterkit-0.2.0.dist-info/METADATA
flask_starterkit-0.2.0.dist-info/RECORD
flask_starterkit-0.2.0.dist-info/WHEEL
flask_starterkit-0.2.0.dist-info/metadata.json
flask_starterkit-0.2.0.dist-info/top_level.txt
starterkit/__init__.py
starterkit/app.py
starterkit/babel.py
starterkit/commands.py
starterkit/db.py
starterkit/hashedassets.py
starterkit/migrate.py
starterkit/sentry.py
starterkit/signals.py
starterkit/unit.py
starterkit/blueprints/__init__.py
starterkit/blueprints/healthcheck.py
starterkit/blueprints/homepage.py
starterkit/settings/__init__.py
starterkit/settings/common.py
starterkit/settings/development.py
starterkit/settings/production.py
starterkit/settings/testing.py
starterkit/templates/starterkit/blueprints/starterkit.html
starterkit/templates/starterkit/blueprints/homepage/homepage.html
starterkit/tests/__init__.py
starterkit/tests/helpers.py
starterkit/tests/test_app.py
starterkit/tests/test_commands.py
starterkit/tests/test_hashedassets.py
starterkit/tests/test_unit.py
starterkit/tests/blueprints/__init__.py
starterkit/tests/blueprints/test_healthcheck.py
starterkit/tests/blueprints/test_homepage.py
starterkit/translations/es/LC_MESSAGES/messages.mo
starterkit/translations/es/LC_MESSAGES/messages.po
