Metadata-Version: 2.0
Name: flask-starterkit
Version: 0.2.0
Summary: UNKNOWN
Home-page: https://www.starterkit.xyz
Author: The Starterkit Corporation
Author-email: hello@starterkit.xyz
License: UNKNOWN
Platform: UNKNOWN
Requires-Dist: blinker (==1.4)
Requires-Dist: flask-admin (==1.5.2)
Requires-Dist: flask-babel (==0.11.2)
Requires-Dist: flask-migrate (==2.3.0)
Requires-Dist: flask-script (==2.0.6)
Requires-Dist: flask-sqlalchemy (==2.3.2)
Requires-Dist: flask (==1.0.2)
Requires-Dist: psycopg2-binary (==2.7.5)
Requires-Dist: pyyaml (==3.13)
Requires-Dist: raven[flask] (==6.9.0)
Requires-Dist: sqlalchemy-utils (==0.33.6)
